tanji/__init__.py
tanji/asymmetric.py
tanji/secrets.py
tanji/symmetric.py
tanji/tanji.py
tanji-1.0.3.dist-info/METADATA
tanji-1.0.3.dist-info/WHEEL
tanji-1.0.3.dist-info/RECORD
