Metadata-Version: 2.1
Name: tanji
Version: 1.0.3
Summary: Tanji is a Python encryption library that provides a secure and flexible solution for encrypting and decrypting messages. It leverages both symmetric and asymmetric encryption techniques to ensure the confidentiality and integrity of your data.
License: MIT
Author: Anupam Maurya
Author-email: anupammaurya981@gmail.com
Requires-Python: >=3.11,<4.0
Classifier: Development Status :: 3 - Alpha
Classifier: Intended Audience :: Developers
Classifier: License :: OSI Approved :: MIT License
Classifier: Programming Language :: Python :: 3
Classifier: Programming Language :: Python :: 3.11
Classifier: Programming Language :: Python :: 3.12
Classifier: Topic :: Software Development :: Build Tools
Requires-Dist: cffi (>=1.16.0,<2.0.0)
Requires-Dist: colorama (>=0.4.6,<0.5.0)
Requires-Dist: cryptography (>=41.0.5,<42.0.0)
Requires-Dist: iniconfig (>=2.0.0,<3.0.0)
Requires-Dist: packaging (>=23.2,<24.0)
Requires-Dist: pluggy (>=1.3.0,<2.0.0)
Requires-Dist: pycparser (>=2.21,<3.0)
Requires-Dist: pytest (>=7.4.3,<8.0.0)
